{"version":3,"kind":"Article","sha256":"a27d062f33ac790eff242f3cc0d83d56efb9367b10ebab54b635d8893623b98a","slug":"release.mystmd-mystmd-1-2-8","location":"/release/mystmd-mystmd-1.2.8.md","dependencies":[],"frontmatter":{"title":"mystmd@1.2.8","tags":["release"],"authors":[{"id":"The Jupyter Book Team","name":"The Jupyter Book Team"}],"date":"2024-06-21","license":{"content":{"id":"CC0-1.0","url":"https://creativecommons.org/licenses/zero/1.0/","name":"Creative Commons Zero v1.0 Universal","free":true,"CC":true}},"github":"https://github.com/jupyter-book/blog","keywords":["Jupyter","JupyterBook","MyST Markdown"],"affiliations":[{"id":"curvenote","name":"Curvenote","url":"https://curvenote.com"},{"id":"2i2c","name":"2i2c","url":"https://2i2c.org"},{"id":"jupyter-book","name":"Jupyter Book","url":"https://compass.jupyterbook.org/team/"},{"id":"Jupyter Book","name":"Jupyter Book"},{"id":"Curvenote","name":"Curvenote"}],"numbering":{"title":{"offset":1}},"source_url":"https://github.com/jupyter-book/blog/blob/main/docs/release/mystmd-mystmd-1.2.8.md","edit_url":"https://github.com/jupyter-book/blog/edit/main/docs/release/mystmd-mystmd-1.2.8.md","exports":[{"format":"md","filename":"mystmd-mystmd-1.2.8.md","url":"/mystmd-mystmd-1.2.8-c56e2c93a42f2a66fb7790e26669ba22.md"}]},"mdast":{"type":"root","children":[{"type":"block","children":[{"type":"paragraph","position":{"start":{"line":11,"column":1},"end":{"line":11,"column":1}},"children":[{"type":"link","url":"https://github.com/jupyter-book/mystmd/releases/tag/mystmd%401.2.8","children":[{"type":"text","value":"Release Source","key":"knOQUyprJv"}],"class":"button","urlSource":"https://github.com/jupyter-book/mystmd/releases/tag/mystmd%401.2.8","error":true,"key":"z1NB6kUPH7"}],"key":"KjIGX81Sj6"},{"type":"heading","depth":2,"position":{"start":{"line":13,"column":1},"end":{"line":13,"column":1}},"children":[{"type":"text","value":"What’s Changed","position":{"start":{"line":13,"column":1},"end":{"line":13,"column":1}},"key":"OI6zecurTh"}],"identifier":"whats-changed","label":"What’s Changed","html_id":"whats-changed","implicit":true,"key":"AfnvBGEuf2"},{"type":"list","ordered":false,"spread":false,"position":{"start":{"line":14,"column":1},"end":{"line":21,"column":1}},"children":[{"type":"listItem","spread":true,"position":{"start":{"line":14,"column":1},"end":{"line":14,"column":1}},"children":[{"type":"paragraph","children":[{"type":"text","value":"📺 Support for HTML video tags by ","position":{"start":{"line":14,"column":1},"end":{"line":14,"column":1}},"key":"koCLsdrWZj"},{"type":"inlineCode","value":"@rowanc1","position":{"start":{"line":14,"column":1},"end":{"line":14,"column":1}},"key":"podnkBeu2r"},{"type":"text","value":" in ","position":{"start":{"line":14,"column":1},"end":{"line":14,"column":1}},"key":"okcf1Qm9i3"},{"type":"link","url":"https://github.com/executablebooks/mystmd/pull/1299","position":{"start":{"line":14,"column":1},"end":{"line":14,"column":1}},"children":[{"type":"text","value":"executablebooks​/mystmd​#1299","key":"cLDc2CAGmK"}],"urlSource":"https://github.com/executablebooks/mystmd/pull/1299","data":{"kind":"issue","org":"executablebooks","repo":"mystmd","issue_number":"1299"},"internal":false,"protocol":"github","key":"tPqUhvFBya"}],"key":"yILU2NXeRv"}],"key":"AEcOPISDty"},{"type":"listItem","spread":true,"position":{"start":{"line":15,"column":1},"end":{"line":15,"column":1}},"children":[{"type":"paragraph","children":[{"type":"text","value":"🐛 Cross references for static sites by ","position":{"start":{"line":15,"column":1},"end":{"line":15,"column":1}},"key":"obh93u2fBT"},{"type":"inlineCode","value":"@rowanc1","position":{"start":{"line":15,"column":1},"end":{"line":15,"column":1}},"key":"Ra6EAJPy7R"},{"type":"text","value":" in ","position":{"start":{"line":15,"column":1},"end":{"line":15,"column":1}},"key":"ql7S7CsVRe"},{"type":"link","url":"https://github.com/executablebooks/mystmd/pull/1302","position":{"start":{"line":15,"column":1},"end":{"line":15,"column":1}},"children":[{"type":"text","value":"executablebooks​/mystmd​#1302","key":"CmS3FrwWsD"}],"urlSource":"https://github.com/executablebooks/mystmd/pull/1302","data":{"kind":"issue","org":"executablebooks","repo":"mystmd","issue_number":"1302"},"internal":false,"protocol":"github","key":"keXLyMwjf7"}],"key":"tzOldkTvrO"}],"key":"A13DBmYFuz"},{"type":"listItem","spread":true,"position":{"start":{"line":16,"column":1},"end":{"line":16,"column":1}},"children":[{"type":"paragraph","children":[{"type":"text","value":"🌄 Fix unsplash images by ","position":{"start":{"line":16,"column":1},"end":{"line":16,"column":1}},"key":"N4AWQIkYTw"},{"type":"inlineCode","value":"@rowanc1","position":{"start":{"line":16,"column":1},"end":{"line":16,"column":1}},"key":"s0TNUvX3nE"},{"type":"text","value":" in ","position":{"start":{"line":16,"column":1},"end":{"line":16,"column":1}},"key":"mG65hjDIk8"},{"type":"link","url":"https://github.com/executablebooks/mystmd/pull/1292","position":{"start":{"line":16,"column":1},"end":{"line":16,"column":1}},"children":[{"type":"text","value":"executablebooks​/mystmd​#1292","key":"QZLQldg8fW"}],"urlSource":"https://github.com/executablebooks/mystmd/pull/1292","data":{"kind":"issue","org":"executablebooks","repo":"mystmd","issue_number":"1292"},"internal":false,"protocol":"github","key":"aBiXT2aJSM"}],"key":"WS8RFBsbKR"}],"key":"cINmuB9GxU"},{"type":"listItem","spread":true,"position":{"start":{"line":17,"column":1},"end":{"line":17,"column":1}},"children":[{"type":"paragraph","children":[{"type":"text","value":"🌎 Allow remote files for template/site options by ","position":{"start":{"line":17,"column":1},"end":{"line":17,"column":1}},"key":"LZUtyFuNOb"},{"type":"inlineCode","value":"@fwkoch","position":{"start":{"line":17,"column":1},"end":{"line":17,"column":1}},"key":"brcZIAEwGt"},{"type":"text","value":" in ","position":{"start":{"line":17,"column":1},"end":{"line":17,"column":1}},"key":"eGEhplR6jT"},{"type":"link","url":"https://github.com/executablebooks/mystmd/pull/1306","position":{"start":{"line":17,"column":1},"end":{"line":17,"column":1}},"children":[{"type":"text","value":"executablebooks​/mystmd​#1306","key":"fB8BFwqIDZ"}],"urlSource":"https://github.com/executablebooks/mystmd/pull/1306","data":{"kind":"issue","org":"executablebooks","repo":"mystmd","issue_number":"1306"},"internal":false,"protocol":"github","key":"JkfdgN66Os"}],"key":"uK6v6n08pH"}],"key":"yEHXgmT38n"},{"type":"listItem","spread":true,"position":{"start":{"line":18,"column":1},"end":{"line":18,"column":1}},"children":[{"type":"paragraph","children":[{"type":"text","value":"🤝 Combine site options when using config extend by ","position":{"start":{"line":18,"column":1},"end":{"line":18,"column":1}},"key":"eKo3crFneP"},{"type":"inlineCode","value":"@fwkoch","position":{"start":{"line":18,"column":1},"end":{"line":18,"column":1}},"key":"s3EvsNg5r1"},{"type":"text","value":" in ","position":{"start":{"line":18,"column":1},"end":{"line":18,"column":1}},"key":"bvZmwbVVKs"},{"type":"link","url":"https://github.com/executablebooks/mystmd/pull/1309","position":{"start":{"line":18,"column":1},"end":{"line":18,"column":1}},"children":[{"type":"text","value":"executablebooks​/mystmd​#1309","key":"pBVga8A9lx"}],"urlSource":"https://github.com/executablebooks/mystmd/pull/1309","data":{"kind":"issue","org":"executablebooks","repo":"mystmd","issue_number":"1309"},"internal":false,"protocol":"github","key":"yhRQxOjfiO"}],"key":"yg4X4udbkp"}],"key":"F0yfbOvA4G"},{"type":"listItem","spread":true,"position":{"start":{"line":19,"column":1},"end":{"line":21,"column":1}},"children":[{"type":"paragraph","children":[{"type":"text","value":"🚀 Release by ","position":{"start":{"line":19,"column":1},"end":{"line":19,"column":1}},"key":"omxDxxlJKr"},{"type":"inlineCode","value":"@github","position":{"start":{"line":19,"column":1},"end":{"line":19,"column":1}},"key":"CHgITfhnEP"},{"type":"text","value":"-actions in ","position":{"start":{"line":19,"column":1},"end":{"line":19,"column":1}},"key":"HQN7gyUqcB"},{"type":"link","url":"https://github.com/executablebooks/mystmd/pull/1300","position":{"start":{"line":19,"column":1},"end":{"line":19,"column":1}},"children":[{"type":"text","value":"executablebooks​/mystmd​#1300","key":"vvvkWuxSvk"}],"urlSource":"https://github.com/executablebooks/mystmd/pull/1300","data":{"kind":"issue","org":"executablebooks","repo":"mystmd","issue_number":"1300"},"internal":false,"protocol":"github","key":"Wx5tn4Bkvz"}],"key":"CXMT34Om2h"}],"key":"XMKbOndy3B"}],"key":"cAFRcSo5nJ"},{"type":"paragraph","position":{"start":{"line":22,"column":1},"end":{"line":22,"column":1}},"children":[{"type":"strong","position":{"start":{"line":22,"column":1},"end":{"line":22,"column":1}},"children":[{"type":"text","value":"Full Changelog","position":{"start":{"line":22,"column":1},"end":{"line":22,"column":1}},"key":"pvzvJEdDwv"}],"key":"Qg3h33K1LD"},{"type":"text","value":": ","position":{"start":{"line":22,"column":1},"end":{"line":22,"column":1}},"key":"GY3VlXsmDY"},{"type":"link","url":"https://github.com/executablebooks/mystmd/compare/mystmd@1.2.7...mystmd@1.2.8","position":{"start":{"line":22,"column":1},"end":{"line":22,"column":1}},"children":[{"type":"text","value":"https://​github​.com​/executablebooks​/mystmd​/compare​/mystmd@1​.2​.7​.​.​.mystmd@1​.2.8","position":{"start":{"line":22,"column":1},"end":{"line":22,"column":1}},"key":"venSbLjUoz"}],"urlSource":"https://github.com/executablebooks/mystmd/compare/mystmd@1.2.7...mystmd@1.2.8","error":true,"key":"vzwpj1DMa6"}],"key":"kUeEZEbMAY"}],"key":"EfZRuhTNmb"}],"key":"eQyy18WJ5G"},"references":{"cite":{"order":[],"data":{}}}}