{"version":3,"kind":"Article","sha256":"6cc5684555240823910cd94ae2b49ba495cff4bfa3b7980020bef0802801bcf2","slug":"release.thebe-thebe-0-9-2","location":"/release/thebe-thebe-0.9.2.md","dependencies":[],"frontmatter":{"title":"thebe@0.9.2","tags":["release"],"authors":[{"id":"The Jupyter Book Team","name":"The Jupyter Book Team"}],"date":"2024-09-06","license":{"content":{"id":"CC0-1.0","url":"https://creativecommons.org/licenses/zero/1.0/","name":"Creative Commons Zero v1.0 Universal","free":true,"CC":true}},"github":"https://github.com/jupyter-book/blog","keywords":["Jupyter","JupyterBook","MyST Markdown"],"affiliations":[{"id":"curvenote","name":"Curvenote","url":"https://curvenote.com"},{"id":"2i2c","name":"2i2c","url":"https://2i2c.org"},{"id":"jupyter-book","name":"Jupyter Book","url":"https://compass.jupyterbook.org/team/"},{"id":"Jupyter Book","name":"Jupyter Book"},{"id":"Curvenote","name":"Curvenote"}],"numbering":{"title":{"offset":1}},"source_url":"https://github.com/jupyter-book/blog/blob/main/docs/release/thebe-thebe-0.9.2.md","edit_url":"https://github.com/jupyter-book/blog/edit/main/docs/release/thebe-thebe-0.9.2.md","exports":[{"format":"md","filename":"thebe-thebe-0.9.2.md","url":"/build/thebe-thebe-0.9.2-11b8fa48b0eac3120c4ef47af37faa28.md"}]},"mdast":{"type":"root","children":[{"type":"block","children":[{"type":"paragraph","position":{"start":{"line":11,"column":1},"end":{"line":11,"column":1}},"children":[{"type":"link","url":"https://github.com/jupyter-book/thebe/releases/tag/thebe%400.9.2","children":[{"type":"text","value":"Release Source","key":"YCBs2E5q5N"}],"class":"button","urlSource":"https://github.com/jupyter-book/thebe/releases/tag/thebe%400.9.2","error":true,"key":"BbZDLQlbW9"}],"key":"Ah8VcSvtHy"},{"type":"heading","depth":2,"position":{"start":{"line":13,"column":1},"end":{"line":13,"column":1}},"children":[{"type":"text","value":"Patch Changes","position":{"start":{"line":13,"column":1},"end":{"line":13,"column":1}},"key":"sPAD5GhnZM"}],"identifier":"patch-changes","label":"Patch Changes","html_id":"patch-changes","implicit":true,"key":"fuMHZMGNuc"},{"type":"list","ordered":false,"spread":false,"position":{"start":{"line":15,"column":1},"end":{"line":21,"column":1}},"children":[{"type":"listItem","spread":true,"position":{"start":{"line":15,"column":1},"end":{"line":15,"column":1}},"children":[{"type":"paragraph","children":[{"type":"text","value":"8c8a55a: Version numbers are printed in debug messages to aid in debugging","position":{"start":{"line":15,"column":1},"end":{"line":15,"column":1}},"key":"jJRmQVdqHi"}],"key":"MWkaWrjIJf"}],"key":"Taj6AqOOXA"},{"type":"listItem","spread":true,"position":{"start":{"line":16,"column":1},"end":{"line":16,"column":1}},"children":[{"type":"paragraph","children":[{"type":"text","value":"Updated dependencies [8c8a55a]","position":{"start":{"line":16,"column":1},"end":{"line":16,"column":1}},"key":"vKWaWPl3MJ"}],"key":"OwfYt2hGeh"}],"key":"hYttllQgMi"},{"type":"listItem","spread":true,"position":{"start":{"line":17,"column":1},"end":{"line":17,"column":1}},"children":[{"type":"paragraph","children":[{"type":"text","value":"Updated dependencies [3d82f84]","position":{"start":{"line":17,"column":1},"end":{"line":17,"column":1}},"key":"haIMgn9Kvf"}],"key":"geR5i0g74o"}],"key":"CPBQ7KRbHZ"},{"type":"listItem","spread":true,"position":{"start":{"line":18,"column":1},"end":{"line":18,"column":1}},"children":[{"type":"paragraph","children":[{"type":"text","value":"Updated dependencies [80dfbb9]","position":{"start":{"line":18,"column":1},"end":{"line":18,"column":1}},"key":"Oa4JllSF8W"}],"key":"F8lLvrjvS9"}],"key":"HlHmNaymHG"},{"type":"listItem","spread":true,"position":{"start":{"line":19,"column":1},"end":{"line":21,"column":1}},"children":[{"type":"paragraph","children":[{"type":"text","value":"Updated dependencies [4b7434e]","position":{"start":{"line":19,"column":1},"end":{"line":19,"column":1}},"key":"wN1UOzhCQ5"}],"key":"C5VuVIATiv"},{"type":"list","ordered":false,"spread":false,"position":{"start":{"line":20,"column":1},"end":{"line":21,"column":1}},"children":[{"type":"listItem","spread":true,"position":{"start":{"line":20,"column":1},"end":{"line":21,"column":1}},"children":[{"type":"paragraph","children":[{"type":"text","value":"thebe-core@0.4.10","position":{"start":{"line":20,"column":1},"end":{"line":20,"column":1}},"key":"oPvTWrJcNj"}],"key":"Yute4a7QKD"}],"key":"jtOdEPuKoq"}],"key":"t6l3edWGUH"}],"key":"JIc4J26Bxu"}],"key":"iCmuREKUYg"}],"key":"hnxP48NvVS"}],"key":"IDuY5tg1aY"},"references":{"cite":{"order":[],"data":{}}},"footer":{"navigation":{"prev":{"title":"thebe@0.9.0","url":"/release/thebe-thebe-0-9-0","group":"Jupyter Book: Blog"},"next":{"title":"thebe-core@0.4.9","url":"/release/thebe-thebe-core-0-4-9","group":"Jupyter Book: Blog"}}},"domain":"http://localhost:3000"}